robo/__init__.py
robo/__main__.py
robo/_argdispatch.py
robo/_callback.py
robo/_collect_tasks.py
robo/_exceptions.py
robo/_hooks.py
robo/_log_auto_setup.py
robo/_log_output_setup.py
robo/_protocols.py
robo/_task.py
robo/cli.py
robo/decorators.py
robocorp_core-0.1.3.dist-info/METADATA
robocorp_core-0.1.3.dist-info/WHEEL
robocorp_core-0.1.3.dist-info/RECORD
