Metadata-Version: 2.1
Name: robocorp-core
Version: 0.1.3
Summary: The automation framework for Python
Author: Ossi R.
Author-email: ossi@robocorp.com
Requires-Python: >=3.9,<4.0
Classifier: Programming Language :: Python :: 3
Classifier: Programming Language :: Python :: 3.9
Classifier: Programming Language :: Python :: 3.10
Classifier: Programming Language :: Python :: 3.11
Requires-Dist: robocorp-logging (==0.0.8)
